{
    "BotToken": "Bot Token Here",
    "options": {
        "poolName": "Pool Name Here",
        "poolAPIStats": "Pool Dommain Here /api/stats",
        "poolTipAddress": "Pool Donation Address Here",
        "poolAddress": "Stratum Address Here",
        "poolFee": "Pool Fee Here%",
        "shouldGreetUser": true,
        "introductionChannel": "Introduction Channel Here",
        "shouldAddGPUCPURoles": true,
        "shoutChannel": "Shout Channel Here",
        "GPURole": "GPU Role Here",
        "CPURole": "CPU Role Here"
    },
    "block": {
        "total": 0,
        "last": 0
    },
    "stats": {
        "fastestBlocktime": 111111111111111111111,
        "fastestBlocktimeString": "Not available yet",
        "highestHashRate": 0,
        "highestHashRateString": "0",
        "highestWorkercount": 0,
        "highestIndividualHashRate": 0,
        "highestIndividualWorker": {}
    },
    "history": []
}